flippr/__about__.py
flippr/__init__.py
flippr/combine.py
flippr/datatypes.py
flippr/functions.py
flippr/parameters.py
flippr/py.typed
flippr/reader.py
flippr/validate.py
flippr-0.2.2.dist-info/METADATA
flippr-0.2.2.dist-info/WHEEL
flippr-0.2.2.dist-info/licenses/LICENSE
flippr-0.2.2.dist-info/RECORD
