Metadata-Version: 2.4
Name: flippr
Version: 0.2.2
Summary: FragPipe Limited-Proteolysis Processor (FLiPPR) is modular, fast, and easy-to-use data processing tool for LiP-MS & LFQ-based experiments analyzed in FragPipe
Project-URL: Documentation, https://github.com/FriedLabJHU/FragPipe-Limited-Proteolysis-Processor#readme
Project-URL: Issues, https://github.com/FriedLabJHU/FragPipe-Limited-Proteolysis-Processorissues
Project-URL: Source, https://github.com/FriedLabJHU/FragPipe-Limited-Proteolysis-Processor
Author-email: Edgar Manriquez-Sandoval <mansanlab@gmail.com>
Maintainer-email: "FriedLab@JHU" <friedlab.jhu@gmail.com>, "Stephen D. Fried" <sdfried@jhu.edu>, Edgar Manriquez-Sandoval <mansanlab@gmail.com>
License-File: LICENSE
Keywords: computational mass spectrometry,differential analysis,flippr,fragpipe,label-free quantification,lfq,limited proteolysis,lip-ms,proteomics
Classifier: Development Status :: 4 - Beta
Classifier: Programming Language :: Python
Classifier: Programming Language :: Python :: 3.12
Classifier: Programming Language :: Python :: 3.13
Classifier: Programming Language :: Python :: 3.14
Classifier: Programming Language :: Python :: Implementation :: CPython
Classifier: Programming Language :: Python :: Implementation :: PyPy
Requires-Python: >=3.12
Requires-Dist: numpy>=2.3
Requires-Dist: polars>=1.33
Requires-Dist: scipy>=1.16
